pythonik/__init__.py
pythonik/client.py
pythonik/constants.py
pythonik/exceptions.py
pythonik/models/__init__.py
pythonik/models/assets/__init__.py
pythonik/models/assets/assets.py
pythonik/models/assets/segments.py
pythonik/models/base.py
pythonik/models/files/__init__.py
pythonik/models/files/file.py
pythonik/models/files/format.py
pythonik/models/files/keyframe.py
pythonik/models/files/proxy.py
pythonik/models/files/storage.py
pythonik/models/jobs/__init__.py
pythonik/models/jobs/job_body.py
pythonik/models/jobs/job_response.py
pythonik/models/metadata/__init__.py
pythonik/models/metadata/views.py
pythonik/models/mutation/__init__.py
pythonik/models/mutation/metadata/__init__.py
pythonik/models/mutation/metadata/mutate.py
pythonik/models/search/__init__.py
pythonik/models/search/search_body.py
pythonik/models/search/search_response.py
pythonik/specs/__init__.py
pythonik/specs/assets.py
pythonik/specs/base.py
pythonik/specs/files.py
pythonik/specs/jobs.py
pythonik/specs/metadata.py
pythonik/specs/search.py
pythonik/tests/__init__.py
pythonik/tests/test_assets.py
pythonik/tests/test_files.py
pythonik/tests/test_jobs.py
pythonik/tests/test_metadata.py
pythonik/tests/test_search.py
pythonik/tests/utils.py
py_iconik-0.6.0.dist-info/LICENSE
py_iconik-0.6.0.dist-info/METADATA
py_iconik-0.6.0.dist-info/WHEEL
py_iconik-0.6.0.dist-info/RECORD
